ba_tools/__init__.py
ba_tools/_closest_multi.py
ba_tools/_data.py
ba_tools/analysis.py
ba_tools/enrich.py
ba_tools/preprocessing.py
ba_tools/proximity.py
ba_tools/utils.py
ba_tools-0.8.4.dist-info/LICENSE
ba_tools-0.8.4.dist-info/METADATA
ba_tools-0.8.4.dist-info/WHEEL
ba_tools-0.8.4.dist-info/top_level.txt
ba_tools-0.8.4.dist-info/RECORD
