Metadata-Version: 2.1
Name: ba-tools
Version: 0.8.4
Summary: Feature engineering using ArcGIS Pro with Business Analyst for using quantitative Geography with Machine Learning.
Home-page: https://github.com/knu2xs/ba-tools
Author: Joel McCune
Author-email: jmccune@esri.com
License: Apache 2.0
Platform: UNKNOWN
Classifier: Development Status :: 4 - Beta
Classifier: Intended Audience :: Developers
Classifier: Programming Language :: Python :: 3 :: Only
Classifier: License :: OSI Approved :: MIT License
Classifier: Operating System :: Microsoft :: Windows
Classifier: Topic :: Scientific/Engineering :: GIS
Requires-Dist: arcgis (>=1.8.2)
Requires-Dist: numpy
Requires-Dist: pandas
Requires-Dist: requests
Requires-Dist: scikit-learn
